bisk/__init__.py
bisk/base.py
bisk/helpers.py
bisk/legacy_seeding.py
bisk/single_robot.py
bisk/assets/halfcheetah.xml
bisk/assets/humanoid.xml
bisk/assets/humanoidamasspc.xml
bisk/assets/humanoidcmupc.xml
bisk/assets/humanoidpc.xml
bisk/assets/lava.png
bisk/assets/net.png
bisk/assets/testcube.xml
bisk/assets/testcube2d.xml
bisk/assets/walker.xml
bisk/features/__init__.py
bisk/features/base.py
bisk/features/joints.py
bisk/tasks/__init__.py
bisk/tasks/butterflies.py
bisk/tasks/gaps.py
bisk/tasks/goalwall.py
bisk/tasks/gototarget.py
bisk/tasks/hurdles.py
bisk/tasks/hurdleslimbo.py
bisk/tasks/limbo.py
bisk/tasks/polebalance.py
bisk/tasks/rundir.py
bisk/tasks/stairs.py
bisk/tasks/velocitycontrol.py
bipedal_skills-2.0.dist-info/LICENSE
bipedal_skills-2.0.dist-info/METADATA
bipedal_skills-2.0.dist-info/WHEEL
bipedal_skills-2.0.dist-info/top_level.txt
bipedal_skills-2.0.dist-info/RECORD
