Metadata-Version: 2.1
Name: bipedal-skills
Version: 2.0
Summary: Bipedal Skills RL Benchmark
Home-page: https://facebookresearch.github.io/hsd3
Author: Meta AI Research
Author-email: jgehring@meta.com
License: MIT License
Requires-Python: >=3.7
License-File: LICENSE
Requires-Dist: dm-control (>=0.0.32)
Requires-Dist: gym (>=0.26)
Requires-Dist: numpy (>=1.9.0)
